albow/ItemRefInsertionException.py
albow/References.py
albow/__init__.py
albow/profiling.py
albow/utils.py
albow/vectors.py
albow/version.py
albow/choices/ImageMultiChoice.py
albow/choices/MultiChoice.py
albow/choices/TextMultiChoice.py
albow/choices/__init__.py
albow/containers/GridView.py
albow/containers/ImageArray.py
albow/containers/PaletteView.py
albow/containers/TabPanel.py
albow/containers/__init__.py
albow/core/CoreUtilities.py
albow/core/DummySound.py
albow/core/RectUtility.py
albow/core/ResourceUtility.py
albow/core/ScheduledCall.py
albow/core/Scheduler.py
albow/core/UserEventCall.py
albow/core/__init__.py
albow/core/exceptions/ApplicationException.py
albow/core/exceptions/CancelException.py
albow/core/exceptions/__init__.py
albow/core/ui/AlbowEventLoop.py
albow/core/ui/AlbowRect.py
albow/core/ui/EventLoopParams.py
albow/core/ui/Predictor.py
albow/core/ui/RootWidget.py
albow/core/ui/Screen.py
albow/core/ui/Shell.py
albow/core/ui/Widget.py
albow/core/ui/__init__.py
albow/demo/AlbowDemo.py
albow/demo/AlbowDemoScreen.py
albow/demo/AlbowDemoShell.py
albow/demo/AlbowDemoSpecialTabs.py
albow/demo/DemoShell.py
albow/demo/GridDebugMain.py
albow/demo/GridDebugShell.py
albow/demo/ScheduledEventTabPage.py
albow/demo/__init__.py
albow/demo/demo.py
albow/demo/loggingConfiguration.json
albow/demo/Resources/.DS_Store
albow/demo/Resources/fonts/COPYRIGHT.TXT
albow/demo/Resources/fonts/README.TXT
albow/demo/Resources/fonts/RELEASENOTES.TXT
albow/demo/Resources/fonts/Vera.ttf
albow/demo/Resources/fonts/VeraBd.ttf
albow/demo/Resources/images/EnterpriseD.png
albow/demo/Resources/images/KlingonD7.png
albow/demo/Resources/images/ball.gif
albow/demo/Resources/images/ball_disabled.png
albow/demo/Resources/images/ball_enabled.png
albow/demo/Resources/images/ball_highlighted.png
albow/demo/Resources/images/biohazard.png
albow/demo/Resources/images/fruit.png
albow/demo/Resources/images/medfighter.png
albow/demo/Resources/music/.DS_Store
python3_albow-2.90.0.dist-info/LICENSE
python3_albow-2.90.0.dist-info/METADATA
python3_albow-2.90.0.dist-info/WHEEL
python3_albow-2.90.0.dist-info/top_level.txt
python3_albow-2.90.0.dist-info/RECORD
