Metadata-Version: 2.1
Name: python3-albow
Version: 2.90.0
Summary: A Little Bit of Widgetry for PyGame
Home-page: https://github.com/hasii2011/albow-python-3
Author: Humberto A. Sanchez II
Author-email: Humberto.A.Sanchez.II@gmail.com
License: UNKNOWN
Platform: UNKNOWN
Requires-Dist: pygame
